README.rst
setup.py
footballdata/ClubElo.py
footballdata/FiveThirtyEight.py
footballdata/MatchHistory.py
footballdata/__init__.py
footballdata/_common.py
footballdata/helper.py
footballdata.egg-info/PKG-INFO
footballdata.egg-info/SOURCES.txt
footballdata.egg-info/dependency_links.txt
footballdata.egg-info/requires.txt
footballdata.egg-info/top_level.txt