Metadata-Version: 1.1
Name: footballdata
Version: 0.3.1
Summary: A collection of wrappers over football (soccer) data from various websites / APIs. You get: Pandas dataframes with sensible, matching column names and identifiers across datasets. Data is downloaded when needed and cached locally. Example Jupyter Notebooks are in the Github repo.
Home-page: https://github.com/skagr/footballdata
Author: Skag Rijsdijk
Author-email: skag.rijsdijk@gmail.com
License: MIT
Keywords: football,soccer,metrics,sports,statistics
Platform: UNKNOWN
Classifier: Development Status :: 4 - Beta
Classifier: License :: OSI Approved :: MIT License
Classifier: Topic :: Software Development :: Libraries
Classifier: Programming Language :: Python
Classifier: Programming Language :: Python :: 2
Classifier: Programming Language :: Python :: 2.7
Classifier: Programming Language :: Python :: 3
Classifier: Programming Language :: Python :: 3.2
Classifier: Programming Language :: Python :: 3.3
Classifier: Programming Language :: Python :: 3.4
Classifier: Programming Language :: Python :: 3.5
Classifier: Programming Language :: Python :: 3.6
